median_voting/__init__.py
median_voting/median_voting.py
median_voting-0.1.1.dist-info/DESCRIPTION.rst
median_voting-0.1.1.dist-info/METADATA
median_voting-0.1.1.dist-info/RECORD
median_voting-0.1.1.dist-info/WHEEL
median_voting-0.1.1.dist-info/metadata.json
median_voting-0.1.1.dist-info/top_level.txt
