Metadata-Version: 2.0
Name: median-voting
Version: 0.1.1
Summary: A python implementation for median votings with the possibility to have weighted votes.
Home-page: https://github.com/FabianWe/median_voting
Author: Fabian Wenzelmann
Author-email: fabianwen@posteo.eu
License: MIT
Keywords: voting median
Platform: UNKNOWN
Requires-Dist: pytest
